mkdocs_excluder/__init__.py
mkdocs_excluder/plugin.py
mkdocs_excluder_plugin-0.0.4.dist-info/LICENSE
mkdocs_excluder_plugin-0.0.4.dist-info/METADATA
mkdocs_excluder_plugin-0.0.4.dist-info/WHEEL
mkdocs_excluder_plugin-0.0.4.dist-info/entry_points.txt
mkdocs_excluder_plugin-0.0.4.dist-info/top_level.txt
mkdocs_excluder_plugin-0.0.4.dist-info/RECORD
