Metadata-Version: 2.1
Name: mkdocs-excluder-plugin
Version: 0.0.4
Summary: A mkdocs plugin that lets you exclude files or trees and removes navigation entries.
Author: polygoniq
Author-email: zdeno@polygoniq.com
License: Apache
Requires-Python: >=3
License-File: LICENSE
Requires-Dist: mkdocs
